autodistill_paligemma/__init__.py
autodistill_paligemma/paligemma_model.py
autodistill_paligemma-0.1.1.dist-info/METADATA
autodistill_paligemma-0.1.1.dist-info/WHEEL
autodistill_paligemma-0.1.1.dist-info/top_level.txt
autodistill_paligemma-0.1.1.dist-info/RECORD
