Metadata-Version: 2.1
Name: autodistill-paligemma
Version: 0.1.1
Summary: Auto-label data with a PaliGemma model, or ine-tune a PaLiGemma model using custom data with Autodistill.
Home-page: https://github.com/autodistill/autodistill-paligemma
Author: Roboflow
Author-email: support@roboflow.com
Classifier: Programming Language :: Python :: 3
Classifier: License :: OSI Approved :: MIT License
Classifier: Operating System :: OS Independent
Requires-Python: >=3.7
Requires-Dist: inference
Requires-Dist: supervision
Requires-Dist: numpy
Requires-Dist: torch
Requires-Dist: transformers
Requires-Dist: peft
Requires-Dist: accelerate
Requires-Dist: sentencepiece
Requires-Dist: roboflow
Requires-Dist: autodistill
Requires-Dist: Pillow
Provides-Extra: dev
Requires-Dist: flake8 ; extra == 'dev'
Requires-Dist: black ==22.3.0 ; extra == 'dev'
Requires-Dist: isort ; extra == 'dev'
Requires-Dist: twine ; extra == 'dev'
Requires-Dist: pytest ; extra == 'dev'
Requires-Dist: wheel ; extra == 'dev'
